prettygit/__init__.py
prettygit/__main__.py
prettygit/main.py
prettygit/setup.py
prettygit/icons/icon.ico
prettygit/icons/icon.svg
prettygit-23.0.4.dist-info/METADATA
prettygit-23.0.4.dist-info/WHEEL
prettygit-23.0.4.dist-info/RECORD
