Metadata-Version: 2.1
Name: PrettyGit
Version: 23.0.4
Summary: very simple and user friendly interface for git
Project-URL: Homepage, https://github.com/gmankab/PrettyGit
Project-URL: Bug Tracker, https://github.com/gmankab/PrettyGit/issues
Project-URL: Documentation, https://github.com/gmankab/PrettyGit
Author-email: gmanka <gmankab@gmail.com>
Classifier: License :: OSI Approved :: GNU General Public License v3 (GPLv3)
Classifier: Operating System :: OS Independent
Classifier: Programming Language :: Python :: 3
Requires-Python: >=3.10
Requires-Dist: betterdata==23.0.2
Requires-Dist: easyselect==23.0.0
Requires-Dist: gmanka-yml==23.0.4
Requires-Dist: hatchling
Requires-Dist: rich
Requires-Dist: twine
